pyslurpers/__init__.py
pyslurpers/slurpers.py
pyslurpers/tests.py
pyslurpers/testdata/attributes.xml
pyslurpers/testdata/baez.json
pyslurpers/testdata/balalaika.json
pyslurpers/testdata/balalaika.xml
pyslurpers/testdata/beatles.xml
pyslurpers/testdata/cdata.xml
pyslurpers/testdata/google.config
pyslurpers/testdata/logback.xml
pyslurpers/testdata/singletag.xml
pyslurpers/testdata/tags-illegals.xml
pyslurpers/testdata/test.xml
pyslurpers/testdata/test1.xml
pyslurpers/testdata/test2.xml
pyslurpers-0.1.0.dist-info/LICENSE
pyslurpers-0.1.0.dist-info/METADATA
pyslurpers-0.1.0.dist-info/WHEEL
pyslurpers-0.1.0.dist-info/top_level.txt
pyslurpers-0.1.0.dist-info/RECORD
