Metadata-Version: 2.1
Name: pyslurpers
Version: 0.1.0
Summary: Python slurpers package for simple XML, JSON, config, etc. processing
Home-page: https://github.com/xuthus/pyslurpers
Author: Sergey Yanzin
Author-email: yanzinsg@gmail.com
License: MIT License
Keywords: pyslurpers xml json config cfg ini parse processing
Platform: any
Classifier: Programming Language :: Python :: 3
Classifier: License :: OSI Approved :: MIT License
Classifier: Operating System :: OS Independent
Requires-Python: >=3.4
